README
setup.py
si/__init__.py
si/common.py
si/math.py
si/prefixes.py
si/register.py
si.egg-info/PKG-INFO
si.egg-info/SOURCES.txt
si.egg-info/dependency_links.txt
si.egg-info/top_level.txt
si.egg-info/zip-safe
si/mathmodules/__init__.py
si/mathmodules/python.py
si/mathmodules/sympy.py
si/pylab/__init__.py
si/units/__init__.py
si/units/base.py
si/units/common.py
si/units/derived.py
si/units/exotic.py
si/units/nonsi.py
si/units/other.py
test/__init__.py
