Metadata-Version: 1.0
Name: si
Version: 0.1.1-1
Summary: Module to represent SI units
Home-page: UNKNOWN
Author: chrysn
Author-email: chrysn@fsfe.org
License: GPL
Platform: UNKNOWN
Classifier: Development Status :: 3 - Alpha
Classifier: Intended Audience :: Education
Classifier: Intended Audience :: Science/Research
Classifier: License :: OSI Approved :: GNU General Public License (GPL)
